norilog/__init__.py
norilog/static/index.css
norilog/templates/index.html
norilog_tenpy2-1.0.0.dist-info/LICENSE.txt
norilog_tenpy2-1.0.0.dist-info/METADATA
norilog_tenpy2-1.0.0.dist-info/WHEEL
norilog_tenpy2-1.0.0.dist-info/entry_points.txt
norilog_tenpy2-1.0.0.dist-info/top_level.txt
norilog_tenpy2-1.0.0.dist-info/RECORD
