Metadata-Version: 2.1
Name: norilog-tenpy2
Version: 1.0.0
Summary: The NoriLog web application.
Home-page: https://github.com/tensho9408/norilog
Author: tenshoohashi
Author-email: tenshoohashi@gmail.com
License: UNKNOWN
Keywords: web,norilog
Platform: UNKNOWN
Classifier: Development Status :: 4 - Beta
Classifier: Framework :: Flask
Classifier: License :: OSI Approved :: BSD License
Classifier: Programming Language :: Python
Classifier: Programming Language :: Python :: 3.6
Requires-Dist: Flask
